hello_release_studio-0.1.0.dist-info/licenses/LICENSE
hello_studio/__init__.py
hello_studio/cli.py
hello_release_studio-0.1.0.dist-info/METADATA
hello_release_studio-0.1.0.dist-info/WHEEL
hello_release_studio-0.1.0.dist-info/entry_points.txt
hello_release_studio-0.1.0.dist-info/top_level.txt
hello_release_studio-0.1.0.dist-info/RECORD
