Metadata-Version: 2.4
Name: hello-release-studio
Version: 0.1.0
Summary: A tiny sample package to test PyPI Release Studio
Author: Sample Author
License: MIT
Project-URL: Homepage, https://example.com/hello-release-studio
Keywords: example,hello,release,studio
Classifier: Programming Language :: Python :: 3
Classifier: Programming Language :: Python :: 3 :: Only
Classifier: License :: OSI Approved :: MIT License
Classifier: Operating System :: OS Independent
Requires-Python: >=3.8
License-File: LICENSE
Dynamic: license-file
